yex/__init__.py
yex/__main__.py
yex/document.py
yex/exception.py
yex/filename.py
yex/io.py
yex/put.py
yex/register.py
yex/util.py
yex/wrap.py
yex/box/__init__.py
yex/box/box.py
yex/box/gismo.py
yex/box/hvbox.py
yex/control/__init__.py
yex/control/arithmetic.py
yex/control/box.py
yex/control/conditional.py
yex/control/control.py
yex/control/debug.py
yex/control/font.py
yex/control/gismo.py
yex/control/hyphen.py
yex/control/io.py
yex/control/log.py
yex/control/macro.py
yex/control/math.py
yex/control/other.py
yex/control/parameter.py
yex/control/register.py
yex/control/string.py
yex/control/tab.py
yex/control/table.py
yex/font/__init__.py
yex/font/__main__.py
yex/font/default.py
yex/font/font.py
yex/font/nullfont.py
yex/font/pk.py
yex/font/tfm.py
yex/mode/__init__.py
yex/mode/horizontal.py
yex/mode/math.py
yex/mode/mode.py
yex/mode/vertical.py
yex/output/__init__.py
yex/output/superclass.py
yex/output/svg.py
yex/output/svg_template.py
yex/parse/__init__.py
yex/parse/expander.py
yex/parse/source.py
yex/parse/token.py
yex/parse/tokeniser.py
yex/parse/tokenstream.py
yex/value/__init__.py
yex/value/dimen.py
yex/value/glue.py
yex/value/muglue.py
yex/value/number.py
yex/value/tokenlist.py
yex/value/value.py
yex-0.1.4.dist-info/LICENSE
yex-0.1.4.dist-info/METADATA
yex-0.1.4.dist-info/WHEEL
yex-0.1.4.dist-info/entry_points.txt
yex-0.1.4.dist-info/top_level.txt
yex-0.1.4.dist-info/RECORD
