Metadata-Version: 2.1
Name: yex
Version: 0.1.4
Summary: Typeset beautifully. TeX workalike.
Home-page: https://gitlab.org/marnanel/yex
Author: Marnanel Thurman
Author-email: marnanel@thurman.org.uk
License: GPL-2
Classifier: Development Status :: 2 - Pre-Alpha
Requires-Python: >=3.0
License-File: LICENSE
Requires-Dist: appdirs (==1.4.4)
Requires-Dist: pytest (==5.3.5)
Requires-Dist: pyfakefs (==4.5.4)
Requires-Dist: Pillow (==9.0.0)
Requires-Dist: pylint (==2.4.4)
